prototools/__init__.py
prototools/canvas.py
prototools/colorize.py
prototools/components.py
prototools/config.py
prototools/constants.py
prototools/decorators.py
prototools/exp.py
prototools/gui.py
prototools/inputs.py
prototools/keyboard.py
prototools/letters.py
prototools/menu.py
prototools/protodb.py
prototools/protomysql.py
prototools/protosql.py
prototools/tabulate.py
prototools/tailwind.py
prototools/tree.py
prototools/utils.py
prototools/validators.py
prototools-0.1.32.8.dist-info/LICENSE
prototools-0.1.32.8.dist-info/METADATA
prototools-0.1.32.8.dist-info/WHEEL
prototools-0.1.32.8.dist-info/top_level.txt
prototools-0.1.32.8.dist-info/RECORD
