Metadata-Version: 2.1
Name: prototools
Version: 0.1.32.8
Summary: console toolbox
Home-page: https://proto-tools.github.io/docs/
Author: Miguel Kanashiro
Author-email: leugimkm@systrien.com
License: MIT
Project-URL: Bug Tracker, https://github.com/proto-tools/docs/issues
Classifier: License :: OSI Approved :: MIT License
Classifier: Programming Language :: Python :: 3.7
Classifier: Programming Language :: Python :: 3.8
Classifier: Programming Language :: Python :: 3.9
Classifier: Intended Audience :: Developers
Classifier: Operating System :: OS Independent
Classifier: Programming Language :: Python :: Implementation :: CPython
Classifier: Programming Language :: Python :: Implementation :: PyPy
Classifier: Topic :: Software Development :: Libraries :: Python Modules
License-File: LICENSE
